<?xml version="1.0" encoding="utf-8" ?>
<dwsync>
<file name="alexus.JPG" server="//clear5.grove.ad.uconn.edu/web/nrca/" local="131707853540000000" remote="131707853540000000" Dst="1" />
<file name="angela.jpg" server="//clear5.grove.ad.uconn.edu/web/nrca/" local="131707849940000000" remote="131707849940000000" Dst="1" />
<file name="beatrice.jpg" server="//clear5.grove.ad.uconn.edu/web/nrca/" local="131707848520000000" remote="131707848520000000" Dst="1" />
<file name="brooke.jpg" server="//clear5.grove.ad.uconn.edu/web/nrca/" local="131707850440000000" remote="131707850430000000" Dst="1" />
<file name="camryn.jpg" server="//clear5.grove.ad.uconn.edu/web/nrca/" local="131707848760000000" remote="131707848750000000" Dst="1" />
<file name="chelsey.jpg" server="//clear5.grove.ad.uconn.edu/web/nrca/" local="131707850180000000" remote="131707850170000000" Dst="1" />
<file name="dillon.jpg" server="//clear5.grove.ad.uconn.edu/web/nrca/" local="131707849360000000" remote="131707849350000000" Dst="1" />
<file name="eric.jpg" server="//clear5.grove.ad.uconn.edu/web/nrca/" local="131707850240000000" remote="131707850230000000" Dst="1" />
<file name="gale.jpg" server="//clear5.grove.ad.uconn.edu/web/nrca/" local="131707850880000000" remote="131707850870000000" Dst="1" />
<file name="garret.jpg" server="//clear5.grove.ad.uconn.edu/web/nrca/" local="131707847980000000" remote="131707847980000000" Dst="1" />
<file name="grace.jpg" server="//clear5.grove.ad.uconn.edu/web/nrca/" local="131707849580000000" remote="131707849570000000" Dst="1" />
<file name="hannah.jpg" server="//clear5.grove.ad.uconn.edu/web/nrca/" local="131707847780000000" remote="131707847780000000" Dst="1" />
<file name="Hayley.jpg" server="//clear5.grove.ad.uconn.edu/web/nrca/" local="131707849060000000" remote="131707849050000000" Dst="1" />
<file name="IMG_1414.JPG" server="//clear5.grove.ad.uconn.edu/web/nrca/" local="131707854900000000" remote="131707854900000000" Dst="1" />
<file name="jennifer.jpg" server="//clear5.grove.ad.uconn.edu/web/nrca/" local="131707851180000000" remote="131707851170000000" Dst="1" />
<file name="jeremy.jpg" server="//clear5.grove.ad.uconn.edu/web/nrca/" local="131707849440000000" remote="131707849440000000" Dst="1" />
<file name="kelci.jpg" server="//clear5.grove.ad.uconn.edu/web/nrca/" local="131707849120000000" remote="131707849120000000" Dst="1" />
<file name="Krissy.jpg" server="//clear5.grove.ad.uconn.edu/web/nrca/" local="131707848960000000" remote="131707848950000000" Dst="1" />
<file name="maggie.jpg" server="//clear5.grove.ad.uconn.edu/web/nrca/" local="131707848300000000" remote="131707848300000000" Dst="1" />
<file name="mannat.jpg" server="//clear5.grove.ad.uconn.edu/web/nrca/" local="131707851020000000" remote="131707851010000000" Dst="1" />
<file name="margaret.jpg" server="//clear5.grove.ad.uconn.edu/web/nrca/" local="131707848300000000" remote="131707848300000000" Dst="1" />
<file name="margret.jpg" server="//clear5.grove.ad.uconn.edu/web/nrca/" local="131707848300000000" remote="131707848300000000" Dst="1" />
<file name="sierra.jpg" server="//clear5.grove.ad.uconn.edu/web/nrca/" local="131707855080000000" remote="131707855080000000" Dst="1" />
<file name="tabitha.jpg" server="//clear5.grove.ad.uconn.edu/web/nrca/" local="131707849260000000" remote="131707849250000000" Dst="1" />
<file name="TJ.jpg" server="//clear5.grove.ad.uconn.edu/web/nrca/" local="131707848640000000" remote="131707848640000000" Dst="1" />
<file name="Tori.JPG" server="//clear5.grove.ad.uconn.edu/web/nrca/" local="131707863480000000" remote="131707863480000000" Dst="1" />
<file name="vishal.jpg" server="//clear5.grove.ad.uconn.edu/web/nrca/" local="131673326700000000" remote="131673326690000000" Dst="1" />
</dwsync>